{
  "result": [
    {
      "ariaNumber": null,
      "ariaType": null,
      "comment": "с 25.03.2024 по 08.04.2024: Нетрудоспособность (Болезнь, карантин и т.п.)",
      "freeParticipantCount": 0,
      "freeTicketCount": 0,
      "id": "754",
      "lastDate": null,
      "name": "Аксенов Михаил Владимирович",
      "nearestDate": null
    },
    {
      "ariaNumber": null,
      "ariaType": null,
      "comment": "",
      "freeParticipantCount": 0,
      "freeTicketCount": 0,
      "id": "9",
      "lastDate": null,
      "name": "Амачова Галина Андреевна",
      "nearestDate": null
    },
    {
      "ariaNumber": null,
      "ariaType": null,
      "comment": "",
      "freeParticipantCount": 0,
      "freeTicketCount": 0,
      "id": "455",
      "lastDate": null,
      "name": "Сошнев Иван Васильевич",
      "nearestDate": null
    },
    {
      "ariaNumber": null,
      "ariaType": null,
      "comment": "",
      "freeParticipantCount": 0,
      "freeTicketCount": 0,
      "id": "383",
      "lastDate": null,
      "name": "Якунин Максим Сергеевич",
      "nearestDate": null
    }
  ],
  "success": true,
  "errorCode": 0,
  "message": null,
  "stackTrace": null
}