{
  "result": [
    {
      "ariaNumber": null,
      "ariaType": null,
      "comment": "",
      "freeParticipantCount": 19,
      "freeTicketCount": 19,
      "id": "4",
      "lastDate": "2024-04-04T00:00:00",
      "name": "Коровина Мария Григорьевна",
      "nearestDate": "2024-04-02T00:00:00"
    },
    {
      "ariaNumber": null,
      "ariaType": null,
      "comment": "",
      "freeParticipantCount": 66,
      "freeTicketCount": 66,
      "id": "301",
      "lastDate": "2024-04-05T00:00:00",
      "name": "Прокофьева Юлия Сергеевна",
      "nearestDate": "2024-04-01T00:00:00"
    }
  ],
  "success": true,
  "errorCode": 0,
  "message": null,
  "stackTrace": null
}