{
  "result": [
    {
      "ariaNumber": "",
      "ariaType": null,
      "comment": "",
      "freeParticipantCount": 0,
      "freeTicketCount": 0,
      "id": "дпо20.26D",
      "lastDate": null,
      "name": "Лисицына О. Ю. (до года)",
      "nearestDate": null
    },
    {
      "ariaNumber": "",
      "ariaType": null,
      "comment": "",
      "freeParticipantCount": 0,
      "freeTicketCount": 0,
      "id": "дпо20.26",
      "lastDate": null,
      "name": "Лисицына О.Ю. ",
      "nearestDate": null
    },
    {
      "ariaNumber": "",
      "ariaType": null,
      "comment": "",
      "freeParticipantCount": 0,
      "freeTicketCount": 1,
      "id": "д20.70",
      "lastDate": "2024-04-01T00:00:00",
      "name": "Ябжанова М.П. ",
      "nearestDate": null
    },
    {
      "ariaNumber": "",
      "ariaType": null,
      "comment": "",
      "freeParticipantCount": 0,
      "freeTicketCount": 0,
      "id": "д20.70D",
      "lastDate": null,
      "name": "Ябжанова М.П. (до года). ",
      "nearestDate": null
    }
  ],
  "success": true,
  "errorCode": 0,
  "message": null,
  "stackTrace": null
}