{
  "result": [
    {
      "ariaNumber": "",
      "ariaType": null,
      "comment": null,
      "freeParticipantCount": 0,
      "freeTicketCount": 0,
      "id": "298",
      "lastDate": null,
      "name": "Баимбетова Инесса Дамировна",
      "nearestDate": null
    },
    {
      "ariaNumber": "",
      "ariaType": null,
      "comment": null,
      "freeParticipantCount": 0,
      "freeTicketCount": 0,
      "id": "959",
      "lastDate": null,
      "name": "Бодня Наталия Николаевна",
      "nearestDate": null
    },
    {
      "ariaNumber": "",
      "ariaType": null,
      "comment": null,
      "freeParticipantCount": 0,
      "freeTicketCount": 0,
      "id": "373",
      "lastDate": null,
      "name": "Власова Виктория Александровна",
      "nearestDate": null
    },
    {
      "ariaNumber": "",
      "ariaType": null,
      "comment": null,
      "freeParticipantCount": 0,
      "freeTicketCount": 0,
      "id": "436",
      "lastDate": null,
      "name": "Волковинская Алиса Рамазановна",
      "nearestDate": null
    },
    {
      "ariaNumber": "",
      "ariaType": null,
      "comment": null,
      "freeParticipantCount": 0,
      "freeTicketCount": 0,
      "id": "795",
      "lastDate": null,
      "name": "Гаркуша Юлия Александровна",
      "nearestDate": null
    },
    {
      "ariaNumber": "",
      "ariaType": null,
      "comment": "Детскосельский, ул. Центральная 8 корп.3",
      "freeParticipantCount": 0,
      "freeTicketCount": 0,
      "id": "793",
      "lastDate": null,
      "name": "Горожанкина Наталья Симоновна",
      "nearestDate": null
    },
    {
      "ariaNumber": "",
      "ariaType": null,
      "comment": null,
      "freeParticipantCount": 0,
      "freeTicketCount": 0,
      "id": "63",
      "lastDate": null,
      "name": "Зива Анжелика Сергеевна",
      "nearestDate": null
    },
    {
      "ariaNumber": "",
      "ariaType": null,
      "comment": null,
      "freeParticipantCount": 0,
      "freeTicketCount": 0,
      "id": "789",
      "lastDate": null,
      "name": "Ильченко Светлана Сергеевна",
      "nearestDate": null
    },
    {
      "ariaNumber": "",
      "ariaType": null,
      "comment": null,
      "freeParticipantCount": 0,
      "freeTicketCount": 0,
      "id": "331",
      "lastDate": null,
      "name": "Исаева Ольга Леонидовна",
      "nearestDate": null
    },
    {
      "ariaNumber": "",
      "ariaType": null,
      "comment": null,
      "freeParticipantCount": 0,
      "freeTicketCount": 0,
      "id": "107",
      "lastDate": null,
      "name": "Кольчицкая Надежда Александровна",
      "nearestDate": null
    },
    {
      "ariaNumber": "",
      "ariaType": null,
      "comment": null,
      "freeParticipantCount": 0,
      "freeTicketCount": 0,
      "id": "930",
      "lastDate": null,
      "name": "Компанцев Константин Валерьевич",
      "nearestDate": null
    },
    {
      "ariaNumber": "",
      "ariaType": null,
      "comment": null,
      "freeParticipantCount": 0,
      "freeTicketCount": 0,
      "id": "510",
      "lastDate": null,
      "name": "Лобовикова Ольга Михайловна",
      "nearestDate": null
    },
    {
      "ariaNumber": "",
      "ariaType": null,
      "comment": null,
      "freeParticipantCount": 0,
      "freeTicketCount": 0,
      "id": "791",
      "lastDate": null,
      "name": "Лобовикова Ольга Михайловна",
      "nearestDate": null
    },
    {
      "ariaNumber": "",
      "ariaType": null,
      "comment": null,
      "freeParticipantCount": 0,
      "freeTicketCount": 0,
      "id": "305",
      "lastDate": null,
      "name": "Мищенко Любовь Александровна",
      "nearestDate": null
    },
    {
      "ariaNumber": "",
      "ariaType": null,
      "comment": null,
      "freeParticipantCount": 0,
      "freeTicketCount": 0,
      "id": "788",
      "lastDate": null,
      "name": "Салова Анна Сергеевна",
      "nearestDate": null
    },
    {
      "ariaNumber": "",
      "ariaType": null,
      "comment": null,
      "freeParticipantCount": 4,
      "freeTicketCount": 5,
      "id": "1230",
      "lastDate": "2024-04-01T16:15:00",
      "name": "Турина Полина Николаевна",
      "nearestDate": "2024-04-01T15:15:00"
    },
    {
      "ariaNumber": "",
      "ariaType": null,
      "comment": null,
      "freeParticipantCount": 0,
      "freeTicketCount": 0,
      "id": "1272",
      "lastDate": null,
      "name": "Шевчук Кирилл Александрович",
      "nearestDate": null
    },
    {
      "ariaNumber": "",
      "ariaType": null,
      "comment": null,
      "freeParticipantCount": 0,
      "freeTicketCount": 0,
      "id": "60",
      "lastDate": null,
      "name": "Ярунова Людмила Павловна",
      "nearestDate": null
    },
    {
      "ariaNumber": "",
      "ariaType": null,
      "comment": null,
      "freeParticipantCount": 0,
      "freeTicketCount": 0,
      "id": "517",
      "lastDate": null,
      "name": "Ярунова Людмила Павловна",
      "nearestDate": null
    }
  ],
  "success": true,
  "errorCode": 0,
  "message": null,
  "stackTrace": null
}