{
  "result": [
    {
      "id": "45",
      "ferId": "224",
      "name": "ВОП",
      "countFreeParticipant": 32,
      "countFreeTicket": 151,
      "lastDate": "2024-04-08T00:00:00",
      "nearestDate": "2024-03-25T00:00:00"
    },
    {
      "id": "78",
      "ferId": "27",
      "name": "Терапевт",
      "countFreeParticipant": 3,
      "countFreeTicket": 4,
      "lastDate": "2024-04-08T00:00:00",
      "nearestDate": "2024-03-25T00:00:00"
    }
  ],
  "success": true,
  "errorCode": 0,
  "message": null,
  "stackTrace": null
}